pmultiqc/__init__.py
pmultiqc/cli.py
pmultiqc/images/pmultiqc_logo_dark.png
pmultiqc/images/pmultiqc_logo_report.png
pmultiqc/main.py
pmultiqc/modules/.DS_Store
pmultiqc/modules/__init__.py
pmultiqc/modules/base.py
pmultiqc/modules/common/__init__.py
pmultiqc/modules/common/common_utils.py
pmultiqc/modules/common/dia_utils.py
pmultiqc/modules/common/file_utils.py
pmultiqc/modules/common/histogram.py
pmultiqc/modules/common/logging.py
pmultiqc/modules/common/ms/__init__.py
pmultiqc/modules/common/ms/base.py
pmultiqc/modules/common/ms/diann.py
pmultiqc/modules/common/ms/idxml.py
pmultiqc/modules/common/ms/msinfo.py
pmultiqc/modules/common/ms/mzid.py
pmultiqc/modules/common/ms/mzml.py
pmultiqc/modules/common/ms/mztab.py
pmultiqc/modules/common/ms_io.py
pmultiqc/modules/common/mzidentml_utils.py
pmultiqc/modules/common/plots/__init__.py
pmultiqc/modules/common/plots/dia.py
pmultiqc/modules/common/plots/general.py
pmultiqc/modules/common/plots/id.py
pmultiqc/modules/common/plots/ms.py
pmultiqc/modules/common/stats.py
pmultiqc/modules/core/__init__.py
pmultiqc/modules/core/core.py
pmultiqc/modules/core/section_groups.py
pmultiqc/modules/diann/__init__.py
pmultiqc/modules/diann/diann.py
pmultiqc/modules/fragpipe/__init__.py
pmultiqc/modules/fragpipe/fragpipe.py
pmultiqc/modules/fragpipe/fragpipe_io.py
pmultiqc/modules/maxquant/__init__.py
pmultiqc/modules/maxquant/maxquant.py
pmultiqc/modules/maxquant/maxquant_io.py
pmultiqc/modules/maxquant/maxquant_plots.py
pmultiqc/modules/maxquant/maxquant_utils.py
pmultiqc/modules/mzidentml/__init__.py
pmultiqc/modules/mzidentml/mzidentml.py
pmultiqc/modules/proteobench/__init__.py
pmultiqc/modules/proteobench/proteobench.py
pmultiqc/modules/proteobench/proteobench_utils.py
pmultiqc/modules/quantms/__init__.py
pmultiqc/modules/quantms/assets/css/quantms.css
pmultiqc/modules/quantms/assets/js/axios.min.js
pmultiqc/modules/quantms/assets/js/highcharts.js
pmultiqc/modules/quantms/assets/js/quantms.js
pmultiqc-0.0.40.dist-info/METADATA
pmultiqc-0.0.40.dist-info/WHEEL
pmultiqc-0.0.40.dist-info/entry_points.txt
pmultiqc-0.0.40.dist-info/licenses/LICENSE
pmultiqc-0.0.40.dist-info/RECORD
