Metadata-Version: 2.4
Name: pmultiqc
Version: 0.0.40
Summary: Python package for quality control of proteomics datasets, based on multiqc package
License: MIT
License-File: LICENSE
Keywords: quantms,proteomics,quality control,MultiQC
Author: Yasset Perez-Riverol
Author-email: ypriverol@gmail.com
Requires-Python: >=3.10
Classifier: Development Status :: 4 - Beta
Classifier: Environment :: Console
Classifier: Environment :: Web Environment
Classifier: Intended Audience :: Science/Research
Classifier: License :: OSI Approved :: MIT License
Classifier: Natural Language :: English
Classifier: Operating System :: MacOS :: MacOS X
Classifier: Operating System :: POSIX
Classifier: Operating System :: Unix
Classifier: Programming Language :: JavaScript
Classifier: Programming Language :: Python
Classifier: Programming Language :: Python :: 3
Classifier: Programming Language :: Python :: 3.10
Classifier: Programming Language :: Python :: 3.11
Classifier: Programming Language :: Python :: 3.12
Classifier: Programming Language :: Python :: 3.13
Classifier: Programming Language :: Python :: 3.14
Classifier: Topic :: Scientific/Engineering
Classifier: Topic :: Scientific/Engineering :: Bio-Informatics
Classifier: Topic :: Scientific/Engineering :: Visualization
Requires-Dist: lxml
Requires-Dist: multiqc (>=1.29,<=1.33)
Requires-Dist: numpy (>=1.23)
Requires-Dist: pandas (>=1.5)
Requires-Dist: pyarrow
Requires-Dist: pyopenms (<=3.4.0)
Requires-Dist: pyteomics
Requires-Dist: scikit-learn (>=1.2)
Requires-Dist: sdrf-pipelines (>=0.0.32)
Requires-Dist: statsmodels
Requires-Dist: urllib3 (>=2.6.1)
Project-URL: GitHub, https://github.com/bigbio/pmultiqc
Project-URL: LICENSE, https://github.com/bigbio/pmultiqc/blob/main/LICENSE
Project-URL: Quantms, https://quantms.org
